libname/FilterDepartment.py
libname/__init__.py
libname/dataset_downloading.py
libname/departments_comparison.py
libname/lmwl_filtering.py
libname/map.py
libname/siteinformation_downloading.py
libname/temporalseries.py
WSI_PeruDB-0.1.dist-info/METADATA
WSI_PeruDB-0.1.dist-info/WHEEL
WSI_PeruDB-0.1.dist-info/top_level.txt
WSI_PeruDB-0.1.dist-info/RECORD
